mframe.py
mframe-0.2.2.dist-info/METADATA
mframe-0.2.2.dist-info/WHEEL
mframe-0.2.2.dist-info/top_level.txt
mframe-0.2.2.dist-info/RECORD
