Metadata-Version: 2.1
Name: mframe
Version: 0.2.2
Summary: A lightweight single file DataFrame implementation that works on older Python distrubtions such as Jython.
Home-page: https://github.com/prio/mframe
Author: Jonathan Harrington
Author-email: jonathan@jonharrington.org
License: BSD
Platform: UNKNOWN
Classifier: License :: OSI Approved :: BSD License
Classifier: Programming Language :: Python :: 2.7
Classifier: Programming Language :: Python :: 3.7
Classifier: Programming Language :: Python :: Implementation :: Jython
Classifier: Programming Language :: Python :: Implementation :: CPython
